hisscl/__init__.py
hisscl/ast.py
hisscl/interp.py
hisscl/lexer.py
hisscl/parser.py
hisscl-0.0.4.dist-info/METADATA
hisscl-0.0.4.dist-info/WHEEL
hisscl-0.0.4.dist-info/licenses/LICENSE
hisscl-0.0.4.dist-info/RECORD
