Metadata-Version: 2.3
Name: hisscl
Version: 0.0.4
Summary: A Python HCL parser
Project-URL: Repository, https://gitea.elara.ws/Elara6331/hisscl
Project-URL: GitHub, https://github.com/Elara6331/hisscl
Author-email: Elara6331 <elara@elara.ws>
License: MPL-2.0
Keywords: config,configuration,hashicorp,hcl,parser
Classifier: Development Status :: 4 - Beta
Classifier: Intended Audience :: Developers
Classifier: License :: OSI Approved :: Mozilla Public License 2.0 (MPL 2.0)
Classifier: Topic :: File Formats
Classifier: Topic :: Software Development :: Interpreters
Requires-Python: >=3.8
